__init__.py
ml_model.py
ml_model-0.0.1.dist-info/LICENSE
ml_model-0.0.1.dist-info/METADATA
ml_model-0.0.1.dist-info/WHEEL
ml_model-0.0.1.dist-info/top_level.txt
ml_model-0.0.1.dist-info/RECORD
