Metadata-Version: 2.1
Name: ml_model
Version: 0.0.1
Summary: Utility for making hyperparameter tuning easier
Author-email: Author name here <opensourcecoder11@gmail.com>
Classifier: Programming Language :: Python :: 3
Classifier: License :: OSI Approved :: MIT License
Classifier: Operating System :: OS Independent
Requires-Python: >=3.7
License-File: LICENSE
